Workbook

Sheet Read Me
A1: HAPPY VEGGIE — SRS-Derived Test Case Suite
A2: Test cases generated from HAPPY-VEGGIE-SRS.md (Production-Ready v1.3, 3 Sept 2026) — Round 1 executed 5 Sept 2026
A4: Source document | B4: HAPPY-VEGGIE-SRS.md — github.com/Arsal0336/happy-veggies/tree/main (repo root), cross-checked against docs/ and HAPPY-VEGGIE-DEV-SPEC.md
A5: Scope | B5: Every Functional Requirement (FR), Non-Functional Requirement (NFR), and External Interface Requirement (EIR) in SRS v1.3 has at least one corresponding test case (closely related sub-requirements are grouped into a single test case where they share one observable behavior).
A6: Sheets | B6: 'Functional Test Cases' (FR-xxx, organized by SRS module 3.2.1–3.2.19) · 'Non-Functional Test Cases' (NFR-xxx) · 'External Interface Test Cases' (EIR-xxx) · 'Summary' (coverage dashboard).
A7: Columns | B7: Test Case ID · Module · Req ID(s) — traces to the SRS requirement(s) exercised · Priority (Must/Should/Could, per SRS) · Phase (P0 = MVP, P1 = production-complete, P2 = enhanced) · Test Case Title · Preconditions · Test Steps · Expected Result · Test Type · Status · Defect Ref · Actual Result / Retest Notes.
A8: Status column — Round 1 (5 Sept 2026) | B8: ~55 rows were actually executed against the live build at hv.vtoxi.com and are marked Pass / Fail / Blocked, each with a note in the last column and, where relevant, a Defect Ref (H-1/H-2/H-3, M-1..M-6, L-1..L-3) pointing at the matching finding in Happy_Veggie_QA_Report.html. Every other row is still 'Not Run' — it genuinely wasn't exercised this round, not assumed passing.
A9: Retest workflow after a fix ships | B9: 1) Filter the Status column for 'Fail' or 'Blocked'. 2) Filter Defect Ref for the ID that was fixed (e.g. 'H-1') to find every row it affects. 3) Re-run those steps against the fixed build. 4) Flip Status to 'Pass' (or 'Fail' again if it's still broken) and append a dated line to the retest-notes cell rather than erasing the Round 1 evidence — e.g. '[Retest 12 Sept: Pass — edit/delete now persist]'.
A10: Priority color key | B10: Rows are shaded in the Priority column: pink = Must, yellow = Should, blue = Could.
A11: Status color key | B11: The Status cell itself is shaded: green = Pass, red = Fail, amber = Blocked, white = Not Run.
A12: How to use | B12: Filter by Module, Priority, Phase, Status, or Defect Ref using the table's AutoFilter dropdowns in the header row of each sheet. P0 Must test cases are the minimum bar for the first production release per SRS §6.2.
A13: Not yet covered by this SRS (out of scope per §1.2.3) | B13: Marketplace/e-commerce/payments, IoT/sensor hardware integration, offline-first operation, languages beyond Urdu/English, and any legal guarantee of yield/price/profitability — no test cases are included for these.
A15: Test case counts by sheet
A16: Sheet | B16: Test cases
A17: Functional Test Cases | B17: 99
A18: Non-Functional Test Cases | B18: 22
A19: External Interface Test Cases | B19: 10
A20: Total | B20: =SUM(B17:B19) -> 131

Sheet Summary
A1: Coverage Summary
A3: Priority | B3: Functional | C3: Non-Functional | D3: External Interface | E3: Total
A4: Must | B4: =COUNTIF('Functional Test Cases'!D:D,"Must")+SUMPRODUCT(ISNUMBER(SEARCH("Must/",'Functional Test Cases'!D:D))*1) -> 71 | C4: =COUNTIF('Non-Functional Test Cases'!D:D,"Must")+SUMPRODUCT(ISNUMBER(SEARCH("Must/",'Non-Functional Test Cases'!D:D))*1) -> 20 | D4: =COUNTIF('External Interface Test Cases'!D:D,"Must")+SUMPRODUCT(ISNUMBER(SEARCH("Must/",'External Interface Test Cases'!D:D))*1) -> 9 | E4: =SUM(B4:D4) -> 100
A5: Should | B5: =COUNTIF('Functional Test Cases'!D:D,"Should")+SUMPRODUCT(ISNUMBER(SEARCH("Should/",'Functional Test Cases'!D:D))*1) -> 27 | C5: =COUNTIF('Non-Functional Test Cases'!D:D,"Should")+SUMPRODUCT(ISNUMBER(SEARCH("Should/",'Non-Functional Test Cases'!D:D))*1) -> 2 | D5: =COUNTIF('External Interface Test Cases'!D:D,"Should")+SUMPRODUCT(ISNUMBER(SEARCH("Should/",'External Interface Test Cases'!D:D))*1) -> 1 | E5: =SUM(B5:D5) -> 30
A6: Could | B6: =COUNTIF('Functional Test Cases'!D:D,"Could")+SUMPRODUCT(ISNUMBER(SEARCH("Could/",'Functional Test Cases'!D:D))*1) -> 1 | C6: =COUNTIF('Non-Functional Test Cases'!D:D,"Could")+SUMPRODUCT(ISNUMBER(SEARCH("Could/",'Non-Functional Test Cases'!D:D))*1) -> 0 | D6: =COUNTIF('External Interface Test Cases'!D:D,"Could")+SUMPRODUCT(ISNUMBER(SEARCH("Could/",'External Interface Test Cases'!D:D))*1) -> 0 | E6: =SUM(B6:D6) -> 1
A7: Total | B7: =SUM(B4:B6) -> 99 | C7: =SUM(C4:C6) -> 22 | D7: =SUM(D4:D6) -> 10 | E7: =SUM(E4:E6) -> 131
A10: Status breakdown (all sheets)
A11: Status | B11: Count
A12: Pass | B12: =COUNTIF('Functional Test Cases'!K:K,"Pass")+COUNTIF('Non-Functional Test Cases'!K:K,"Pass")+COUNTIF('External Interface Test Cases'!K:K,"Pass") -> 17
A13: Fail | B13: =COUNTIF('Functional Test Cases'!K:K,"Fail")+COUNTIF('Non-Functional Test Cases'!K:K,"Fail")+COUNTIF('External Interface Test Cases'!K:K,"Fail") -> 19
A14: Blocked | B14: =COUNTIF('Functional Test Cases'!K:K,"Blocked")+COUNTIF('Non-Functional Test Cases'!K:K,"Blocked")+COUNTIF('External Interface Test Cases'!K:K,"Blocked") -> 45
A15: Not Run | B15: =COUNTIF('Functional Test Cases'!K:K,"Not Run")+COUNTIF('Non-Functional Test Cases'!K:K,"Not Run")+COUNTIF('External Interface Test Cases'!K:K,"Not Run") -> 50

Sheet Functional Test Cases
A1: HAPPY VEGGIE — Functional Test Cases
A2: Derived from HAPPY-VEGGIE-SRS.md v1.3 (github.com/Arsal0336/happy-veggies)
A4: Test Case ID | B4: Module | C4: Req ID(s) | D4: Priority | E4: Phase | F4: Test Case Title | G4: Preconditions | H4: Test Steps | I4: Expected Result | J4: Test Type | K4: Status | L4: Defect Ref | M4: Actual Result / Retest Notes (5 Sept 2026 run)
A5: TC-FR-001 | B5: Auth & Profile | C5: FR-001 | D5: Must | E5: P0 | F5: Farmer login via phone + OTP | G5: Farmer has a valid phone number; app installed/open. | H5: 1. Open app, select 'Sign in with phone number'. 2. Enter a valid E.164 phone number. 3. Tap Send OTP. 4. Enter the received OTP. 5. Tap Verify. | I5: OTP is sent, verification succeeds, and the farmer is authenticated and routed into the app. | J5: Functional | K5: Pass | M5: Confirmed working — OTP sign-in (mock mode) completed successfully.
A6: TC-FR-002 | B6: Auth & Profile | C6: FR-001 | D6: Must | E6: P0 | F6: Login rejected with invalid OTP | G6: Farmer has requested an OTP for a valid phone number. | H6: 1. Enter the phone number and request OTP. 2. Enter an incorrect 4-digit code. 3. Tap Verify. | I6: Verification fails with a clear localized error; farmer is not authenticated and may retry. | J6: Functional | K6: Not Run
A7: TC-FR-003 | B7: Auth & Profile | C7: FR-002 | D7: Must | E7: P0 | F7: Owner-scoped data access enforced | G7: Two farmer accounts (A and B) exist, each with at least one farm. | H7: 1. Authenticate as Farmer A. 2. Attempt to fetch/view Farmer B's farm, production area, field, twin, plan, or assistant thread by ID (via UI navigation or direct API call). | I7: Access is denied/404 for Farmer A; only an authorized admin can view another farmer's data. | J7: Functional | K7: Not Run
A8: TC-FR-004 | B8: Auth & Profile | C8: FR-017 | D8: Must | E8: P0 | F8: Unified entry routes new vs returning farmer | G8: A phone number not yet registered, and a second phone number already registered. | H8: 1. Complete OTP verification with the unregistered number. 2. Observe routing. 3. Repeat OTP flow with the registered number. | I8: Unregistered number is routed to first-time profile capture (name/language); registered number is routed directly to the farms dashboard. | J8: Functional | K8: Pass | M8: New-vs-returning-farmer routing confirmed correct.
A9: TC-FR-005 | B9: Auth & Profile | C9: FR-018 | D9: Must | E9: P0 | F9: First-time profile capture (name + language) | G9: Farmer has just completed OTP verification for the first time. | H9: 1. On the first-time profile screen, enter a name. 2. Select a preferred language (English or Urdu). 3. Submit. | I9: Name and language are saved to the farmer profile and used for all subsequent localized content. | J9: Functional | K9: Not Run
A10: TC-FR-006 | B10: Auth & Profile | C10: FR-044 | D10: Must | E10: P0 | F10: Session refresh and revocation | G10: Farmer is logged in with an active session/token. | H10: 1. Let the access token approach expiry and make an authenticated request. 2. Confirm silent refresh occurs. 3. Log out (or revoke session) from Settings. 4. Attempt to use the old token. | I10: Token refresh keeps the session alive transparently; after logout/revocation the old token is rejected on subsequent calls. | J10: Functional | K10: Fail | L10: M-5 | M10: Logout succeeds server-side (session cleared — next navigation redirects to /auth/phone) but Settings gives no feedback and never redirects; looks like the click did nothing. See M-5.
A11: TC-FR-007 | B11: Farm Management | C11: FR-045 | D11: Must | E11: P0 | F11: Create, view, update, soft-delete a farm | G11: Authenticated farmer, no farms yet. | H11: 1. Create a new farm with required fields. 2. View it in 'My farms'. 3. Edit its name/location. 4. Delete the farm. | I11: Farm is created and listed; edits persist; delete performs a soft-delete (farm disappears from the active list but is not physically removed from the database). | J11: Functional | K11: Fail | L11: H-1 | M11: Create (via wizard) works. Edit-name save does not persist ("(unnamed)" remains); Delete removes nothing from the Farms list. See H-1 steps 5-6.
A12: TC-FR-008 | B12: Farm Management | C12: FR-046 | D12: Must | E12: P0 | F12: Farm captures location, area, region, display name | G12: Authenticated farmer creating a farm. | H12: 1. Enter latitude/longitude (or use GPS). 2. Enter total area and unit. 3. Confirm/adjust suggested region. 4. Enter an optional display name. 5. Save. | I12: All four attributes are stored and shown back correctly on the farm detail/dashboard view. | J12: Functional | K12: Pass | M12: All four attributes captured and displayed correctly at creation.
A13: TC-FR-009 | B13: Farm Management | C13: FR-019 | D13: Must | E13: P0 | F13: Area entered in acre/kanal/marla stored canonically in acres | G13: Authenticated farmer creating or editing a farm. | H13: 1. Enter total area as '2 kanal'. 2. Save. 3. Re-open the farm and switch display unit to acres, then to marla. | I13: Stored canonical value is in acres (2 kanal ≈ 0.25 acres); displayed value converts correctly to whichever unit is selected, with no drift after repeated conversions. | J13: Functional | K13: Fail | L13: L-1 | M13: Marla is missing from the setup wizard's unit dropdown, and 'acre'/'acres' are listed twice (Crop Zone form has the correct list). See L-1.
A14: TC-FR-010 | B14: Farm Management | C14: FR-020 | D14: Must | E14: P0 | F14: Region suggested from location, confirmable/changeable | G14: Authenticated farmer entering farm location via GPS or manual lat/long. | H14: 1. Provide a location known to map to 'Islamabad' region. 2. Observe the suggested region. 3. Change it to a different region and save. | I14: Region is auto-suggested from coordinates; farmer's manual override is respected and persisted. | J14: Functional | K14: Fail | L14: L-2 | M14: Same coordinates produced 'Punjab' for a new farm vs 'Islamabad' for the pre-seeded demo farm. See L-2.
A15: TC-FR-011 | B15: Farm Management | C15: FR-003 | D15: Must | E15: P0 | F15: GPS auto-detects and stores lat/long | G15: Authenticated farmer on a device with location services enabled. | H15: 1. Start farm creation. 2. Grant location permission when prompted. 3. Observe latitude/longitude auto-populate. | I15: Coordinates are captured automatically and stored with the farm record. | J15: Functional | K15: Not Run
A16: TC-FR-012 | B16: Farm Management | C16: FR-004 | D16: Could | E16: P0 | F16: Manual location entry when GPS unavailable | G16: Location services denied or unavailable. | H16: 1. Deny/disable GPS. 2. Start farm creation. 3. Use the manual location entry option (address/map pin/lat-long fields). | I16: Farmer can still supply a location manually and proceed with farm creation. | J16: Functional | K16: Not Run
A17: TC-FR-013 | B17: Farm Management | C17: FR-109, FR-111 | D17: Must | E17: P0 | F17: Production Area as first-class child; default Open Field for legacy flow | G17: Authenticated farmer creating a farm without explicitly choosing a production-area type. | H17: 1. Create a farm and add a crop zone/field without selecting a production area type. 2. Inspect the resulting farm structure. | I17: A default 'Open Field' production area is created automatically and the field attaches to it; farm supports zero or more production areas. | J17: Functional | K17: Blocked | L17: H-1 | M17: Add area / Add zone both fail silently — default-area behavior can't be verified. See H-1 steps 1 & 3.
A18: TC-FR-014 | B18: Farm Management | C18: FR-110 | D18: Must | E18: P0 | F18: Production area type catalog is extensible | G18: Admin access to the production area type catalog. | H18: 1. As admin, view existing production area types (open_field, shed, greenhouse, tunnel_polyhouse, experimental, other_protected). 2. Add a new custom type. 3. As a farmer, create a production area using the new type. | I18: Core types are available out of the box; a new type can be added via catalog/admin configuration without a code change, and is selectable when creating a production area. | J18: Functional | K18: Not Run
A19: TC-FR-015 | B19: Farm Management | C19: FR-047, FR-112, FR-113 | D19: Must | E19: P0 | F19: Farm with multiple production areas, multiple crops, multiple environments concurrently | G19: Authenticated farmer with a farm of at least 10 acres. | H19: 1. Add an Open Field production area with two crop zones (different crops). 2. Add a Shed production area with one crop zone. 3. Add an Experimental production area with one crop zone. 4. View the farm structure. | I19: The farm simultaneously contains multiple production areas of different environment types, each with its own crop zone(s), and multiple distinct crops are represented across the farm at once. | J19: Functional | K19: Blocked | L19: H-1 | M19: Add area / Add zone both fail silently — no way to give a farm a second production area or crop zone. See H-1.
A20: TC-FR-016 | B20: Farm Management | C20: FR-048 | D20: Must | E20: P0 | F20: Field/crop zone captures required attributes | G20: A production area exists on a farm. | H20: 1. Add a field/crop zone specifying name, area, crop, optional seed variety, planting date, growth stage, expected yield. 2. Save and reopen the field. | I20: All entered attributes are persisted and displayed, and the field correctly references its parent production area. | J20: Functional | K20: Fail | L20: H-1 | M20: Add-zone form resets to blank on submit; nothing is created. See H-1 step 3.
A21: TC-FR-017 | B21: Farm Management | C21: FR-049, FR-114 | D21: Must | E21: P0 | F21: Land allocation validated against farm total; mixed units supported | G21: A farm with a known total open-field area (e.g., 5 acres) and one shed production area measured in sq ft. | H21: 1. Attempt to allocate open-field crop zones totalling more than 5 acres (beyond configured tolerance). 2. Attempt to allocate a shed crop zone in sq ft. | I21: Over-allocation of open-field/experimental land is rejected or flagged per tolerance; the shed's sq ft allocation is validated independently against its own production-area capacity and does not corrupt open-field accounting. | J21: Functional | K21: Blocked | L21: H-1 | M21: No crop zone can be created to test over-allocation against. See H-1.
A22: TC-FR-018 | B22: Farm Management | C22: FR-050 | D22: Must | E22: P1 | F22: Farm declares one or more water sources with irrigation attributes | G22: Authenticated farmer editing a farm. | H22: 1. Add a tube well water source with capacity/reliability/irrigation method. 2. Add a second water source (e.g., canal). 3. Save. | I22: Both water sources are stored against the farm and available to Water Intelligence and twin views. | J22: Functional | K22: Fail | L22: H-1 | M22: Add water source form resets to blank on submit; list still reads 'No … yet'. See H-1 step 2.
A23: TC-FR-019 | B23: Farm Management | C23: FR-006, FR-021 | D23: Should | E23: P0 | F23: Guided setup wizard tolerates unknowns and still produces a plan | G23: A new farmer with unknown soil type, no budget figure, and no specific crop preference. | H23: 1. Start the new-farmer guided setup wizard. 2. Leave soil as 'unknown', budget blank, and choose 'help me choose' for crop. 3. Complete the wizard. | I23: Wizard completes without requiring the omitted fields and a plan/recommendation is still generated. | J23: Functional | K23: Pass | L23: M-4 | M23: Wizard completes with soil=unknown, budget blank, crop='let AI suggest', and does generate a plan. Caveat: the water-source and first-crop answers shown on the review step are silently dropped and never persisted to the created farm. See M-4.
A24: TC-FR-020 | B24: Farm Management | C24: FR-005 | D24: Must | E24: P0 | F24: Preferred crop captured at farm/area/field level | G24: Authenticated farmer editing a farm. | H24: 1. Set a preferred crop at the farm level. 2. Set a different preferred crop on a specific production area. 3. Set a preferred crop on an individual field. | I24: Each level accepts and stores its own preferred-crop value independently, applied as applicable to recommendations. | J24: Functional | K24: Blocked | L24: H-1 | M24: Area/field-level preferred crop can't be set — creating an area/field fails. See H-1.
A25: TC-FR-021 | B25: Digital Twin | C25: FR-051, FR-115 | D25: Must | E25: P0 | F25: Twin maintains independent state per production area and aggregates at farm level | G25: A farm with an Open Field and a Shed production area, each with crop zones. | H25: 1. Change a crop/attribute in the Shed production area only. 2. View the Shed twin state, then the farm-level twin summary. | I25: The Shed's twin state reflects the change independently; the farm-level summary aggregates data across all production areas including the change. | J25: Functional | K25: Blocked | L25: H-1 | M25: Only one (default) production area could ever be created — no second area to compare independent state against.
A26: TC-FR-022 | B26: Digital Twin | C26: FR-052, FR-116 | D26: Must | E26: P0/P1 | F26: Twin includes full ecosystem state | G26: A farm with production areas, water sources, and at least one activity logged. | H26: 1. Open the farm's Digital Twin view. | I26: Twin displays location, total area, production areas, soil profile (with provenance), water sources, irrigation, weather snapshot, fields/crops, activity summary, economic summary when available, and a sustainability/Green Farm summary placeholder or value. | J26: Functional | K26: Fail | L26: H-1, M-1 | M26: Soil and water sections are permanently empty (forms don't persist, H-1); the weather tile also shows a raw status string instead of a value (M-1).
A27: TC-FR-023 | B27: Digital Twin | C27: FR-053 | D27: Must | E27: P1 | F27: Scheduled and on-demand twin refresh with status | G27: A farm with weather/soil providers configured. | H27: 1. Note current 'last_refreshed_at' timestamp. 2. Wait for the scheduled refresh interval, or trigger a manual refresh. 3. Re-check the twin. | I27: 'last_refreshed_at' updates after the scheduled/on-demand refresh, and provider status (success/degraded/failed) is recorded and visible. | J27: Functional | K27: Fail | L27: M-3 | M27: 'Refresh twin' gives no loading/completion feedback; only an OPTIONS preflight is observed, no visible follow-up. See M-3.
A28: TC-FR-024 | B28: Digital Twin | C28: FR-054 | D28: Must | E28: P0 | F28: Twin summary API/view supports dashboard and assistant grounding | G28: A farm with at least one production area and field. | H28: 1. Call/view the twin summary endpoint or dashboard widget. | I28: Response/view includes a production-area breakdown suitable for both the dashboard UI and as grounding context for the AI Assistant. | J28: Functional | K28: Pass | M28: Assistant answers correctly referenced twin data (farm size, missing crop zones), confirming the summary feeds it.
A29: TC-FR-025 | B29: Digital Twin | C29: FR-055 | D29: Must | E29: P0 | F29: No raw machine output surfaced to farmer | G29: A twin or plan has been generated via LLM. | H29: 1. Inspect all farmer-facing twin and plan outputs (dashboard, plan screen, assistant). | I29: All content is structured, localized, and human-readable; no raw JSON/LLM blob or stack trace is ever shown to the farmer. | J29: Functional | K29: Fail | L29: M-1 | M29: Overview 'Weather' tile renders the literal provider-status enum 'success' instead of the forecast. See M-1.
A30: TC-FR-026 | B30: Farm Twinning / Optimization | C30: FR-029 | D30: Must | E30: P0 | F30: Record multiple crops/fields on one farm | G30: Authenticated farmer with an existing farm. | H30: 1. Add three fields, each with a different crop. | I30: All three fields and their distinct crops are recorded and retrievable. | J30: Functional | K30: Blocked | L30: H-1 | M30: Add zone fails silently for every attempt — no second field/crop can be created. See H-1.
A31: TC-FR-027 | B31: Farm Twinning / Optimization | C31: FR-030 | D31: Must | E31: P0 | F31: Companion-planting compatibility with reasons | G31: A farm with two crop zones planted with a known-incompatible crop pair (e.g., tomato and cabbage-family crop, per compatibility table). | H31: 1. View the crop compatibility panel for the two fields. | I31: Relation is shown as good/avoid/neutral with a localized reason drawn from the companion-planting table. | J31: Functional | K31: Blocked | L31: H-1 | M31: Needs ≥2 real crop zones — zone creation fails. See H-1.
A32: TC-FR-028 | B32: Farm Twinning / Optimization | C32: FR-099, FR-103 | D32: Must | E32: P0 | F32: On-farm neighbouring-field compatibility takes precedence | G32: A farm with Field A adjacent to Field B (incompatible pair) and also containing a non-adjacent Field C with a different incompatible crop. | H32: 1. View compatibility warnings for Field A. | I32: The neighbouring Field B conflict is evaluated and surfaced first/with priority, ahead of same-farm non-adjacent conflicts or anonymized nearby-farm signals. | J32: Functional | K32: Blocked | L32: H-1 | M32: Needs ≥2 real crop zones — zone creation fails. See H-1.
A33: TC-FR-029 | B33: Farm Twinning / Optimization | C33: FR-100 | D33: Should | E33: P1 | F33: Warn on conflicting crop change with alternatives | G33: Field A borders Field B, which grows a crop incompatible with a proposed new crop for Field A. | H33: 1. Attempt to change Field A's crop to the incompatible crop. | I33: System warns of the conflict with Field B and suggests compatible alternative crops/varieties. | J33: Functional | K33: Blocked | L33: H-1 | M33: Needs ≥2 real crop zones — zone creation fails. See H-1.
A34: TC-FR-030 | B34: Farm Twinning / Optimization | C34: FR-101, FR-102, FR-108 | D34: Should | E34: P1 | F34: Neighbouring-farm compatibility uses only anonymized aggregates | G34: Region has sufficient nearby-farm crop data for the farmer's area. | H34: 1. View neighbouring/nearby-farm compatibility insight for a field. 2. Inspect the underlying data/response for any per-farm identifiers. | I34: Insight is labeled as a regional/neighbourhood signal (e.g., 'common nearby crops'); no individual farmer identity or specific neighbour's field map is ever exposed. | J34: Functional | K34: Blocked | L34: H-1 | M34: No UI entry point found for this feature at all; also needs a real crop zone. See H-1.
A35: TC-FR-031 | B35: Farm Twinning / Optimization | C35: FR-104, FR-105, FR-106, FR-107 | D35: Must/Should | E35: P1 | F35: Seed variety suggestions with rationale, and can be accepted | G35: A field with a selected crop but no seed variety, region/season/soil/water context available. | H35: 1. Request seed variety suggestions for the field. 2. Review suggested varieties (name EN/UR, type, rationale, maturity days, water/disease notes, risk). 3. Accept one suggestion. 4. Try 'help me choose variety' with only crop selected. | I35: Suggestions are tailored and complete per the listed attributes; accepting a variety stores it on the field; 'help me choose' works when only the crop is set; plan output may include a recommended variety when catalog data exists. | J35: Functional | K35: Blocked | L35: H-1 | M35: No crop zone can be created to attach a seed variety to. See H-1.
A36: TC-FR-032 | B36: Farm Twinning / Optimization | C36: FR-031, FR-032 | D36: Should/Must | E36: P0/P1 | F36: Care guidance grounded in twin; compatibility still shown if LLM fails | G36: A farm/field set with an LLM provider that can be forced to fail (simulate timeout/error). | H36: 1. Request care guidance under normal conditions. 2. Simulate LLM provider failure and view the field's compatibility results again. | I36: Normal case: LLM guidance reflects twin context (soil, water, variety). Failure case: compatibility results still render correctly without depending on the failed LLM call. | J36: Functional | K36: Blocked | L36: H-1 | M36: Needs a real field/crop zone — zone creation fails. See H-1.
A37: TC-FR-033 | B37: Farm Twinning / Optimization | C37: FR-056, FR-057, FR-058, FR-117 | D37: Must | E37: P1 | F37: Optimal multi-environment portfolio recommendation balances all factors, sustainability never overriding suitability | G37: A farm with open field, shed, and experimental production areas, with water and soil constraints configured. | H37: 1. Request a portfolio optimization/recommendation across the farm. 2. Inspect the rationale for each recommended allocation. 3. Specifically check whether any crop was chosen purely for lower resource use despite unsuitable soil/season/environment or unacceptable yield/risk. | I37: Recommendation spans multiple production environments and land, with rationale referencing yield, economics, water, soil, weather, compatibility, seed variety, risk, diversification, budget, and sustainability jointly — sustainability is never the sole justification for an otherwise unsuitable/low-yield/high-risk choice. | J37: Functional | K37: Blocked | L37: H-1 | M37: Needs multiple real production areas/crop zones — creation fails. See H-1.
A38: TC-FR-034 | B38: Farm Twinning / Optimization | C38: FR-059 | D38: Should | E38: P1 | F38: Portfolio presented as clear per-crop allocation | G38: A generated portfolio recommendation. | H38: 1. View the portfolio recommendation output. | I38: Output is presented as acres/sq ft per crop, including experimental and reserve allocations, grouped by production area where relevant. | J38: Functional | K38: Blocked | L38: H-1 | M38: Needs a generated portfolio recommendation, which needs real crop zones. See H-1.
A39: TC-FR-035 | B39: Farm Twinning / Optimization | C39: FR-007, FR-008, FR-009, FR-010, FR-022, FR-023 | D39: Must/Should | E39: P0 | F39: Custom plan generation with region/season crops, calendar, inputs, structured sections | G39: A farm with location, season context, and (optionally) weather/soil data available. | H39: 1. Request plan generation. 2. Review the resulting plan. | I39: Plan is generated via LLM/deterministic tables from twin inputs; includes region/season-appropriate crops, a step-by-step calendar, water/fertilizer/input guidance; is enriched with weather/soil when available (context_used recorded); and renders as clearly sectioned content, never raw output. | J39: Functional | K39: Pass | M39: LLM plan generation confirmed producing real, sectioned, disclaimer-carrying content.
A40: TC-FR-036 | B40: Farm Twinning / Optimization | C40: FR-024 | D40: Should | E40: P1 | F40: Plan share/export as PDF | G40: A generated plan exists. | H40: 1. Use the share-as-text option. 2. Export the plan as PDF. | I40: Plan text can be shared; PDF export renders correctly with proper formatting (see also NFR-004 for RTL). | J40: Functional | K40: Fail | L40: M-6 | M40: No Share/Export/PDF control exists anywhere on the Plan page — not broken, just not built. See M-6.
A41: TC-FR-037 | B41: Farm Twinning / Optimization | C41: FR-025, FR-012 | D41: Should/Must | E41: P0 | F41: Language change offers regeneration, not silent auto-translate; content in selected language | G41: A generated plan exists in English. | H41: 1. Switch app language to Urdu after the plan is generated. 2. Observe UI and plan behavior. | I41: UI switches to Urdu immediately; the existing plan is not silently auto-translated — farmer is offered plan regeneration in Urdu; newly generated plans/assistant answers appear in the selected language. | J41: Functional | K41: Fail | L41: H-2 | M41: Language never actually switches to Urdu anywhere in the app, so this requirement is unreachable as a direct consequence. See H-2.
A42: TC-FR-038 | B42: AI Farm Assistant | C42: FR-060 | D42: Must | E42: P1 | F42: Every farm has its own scoped assistant | G42: Farmer with two farms, A and B. | H42: 1. Open the assistant for Farm A and ask a farm-specific question. 2. Open the assistant for Farm B. | I42: Farm B's assistant has no memory of or reference to Farm A's conversation or data; each assistant is scoped strictly to its own farm's twin. | J42: Functional | K42: Not Run
A43: TC-FR-039 | B43: AI Farm Assistant | C43: FR-061, FR-118 | D43: Must | E43: P1 | F43: Assistant grounds answers in full twin context, resolving correct production area | G43: A farm with both an open-field cucumber zone and a shed cucumber zone. | H43: 1. Ask the assistant 'How is my shed cucumber crop performing?' 2. Ask 'How is my open field cucumber doing?' | I43: Assistant resolves and answers using the correct production area's twin data in each case (shed vs open field) and never assumes protected crops share outdoor conditions. | J43: Functional | K43: Blocked | L43: H-1 | M43: Only one production area exists on any test farm — can't verify resolution between e.g. shed vs open-field twin data. See H-1.
A44: TC-FR-040 | B44: AI Farm Assistant | C44: FR-062 | D44: Must | E44: P1 | F44: Assistant discloses insufficient data rather than inventing facts | G44: A farm missing soil-test data and with no water source configured. | H44: 1. Ask the assistant a question that depends on missing data (e.g., exact soil pH). | I44: Assistant clearly states the data is unavailable/uncertain rather than fabricating a specific farm fact. | J44: Functional | K44: Pass | M44: Confirmed twice live: assistant explicitly named missing crop-zone/soil/water data rather than fabricating figures (tomato irrigation question, Green Farm Score question).
A45: TC-FR-041 | B45: AI Farm Assistant | C45: FR-063 | D45: Must | E45: P1 | F45: Assistant supports the full range of specified question types | G45: A farm with full twin data (crops, water, weather, history, protected area, Green Score). | H45: 1. Ask each of: what to plant next; which seed variety; best expected return; which field needs water; spraying suitability; yield change; crop compatibility (on-farm and nearby); plan changes; crop risk; last year's performance; what to do this week; protected-area performance; a Green Farm Score question. | I45: Each question type receives a relevant, twin-grounded answer. | J45: Functional | K45: Not Run
A46: TC-FR-042 | B46: AI Farm Assistant | C46: FR-064 | D46: Must | E46: P1 | F46: Assistant conversations persisted per farm, owner-scoped | G46: A farmer has an assistant conversation on Farm A. | H46: 1. Ask a question, close the app, reopen, and revisit Farm A's assistant. 2. As a different farmer, attempt to access Farm A's assistant history. | I46: History is retained and shown to the owning farmer on return; another farmer cannot access it. | J46: Functional | K46: Not Run
A47: TC-FR-043 | B47: AI Farm Assistant | C47: FR-065 | D47: Should | E47: P1 | F47: Assistant cites influencing twin signals | G47: A farm with weather forecast and a shed with humidity data. | H47: 1. Ask a question answerable from weather forecast and shed humidity. | I47: Answer includes a lightweight citation of which signals were used (e.g., 'based on tomorrow's forecast and shed humidity reading'). | J47: Functional | K47: Not Run
A48: TC-FR-044 | B48: AI Farm Assistant | C48: FR-066 | D48: Must | E48: P1 | F48: Assistant never exposes other farmers' private data | G48: Two farmer accounts with distinct private farm data. | H48: 1. As Farmer A, attempt prompt-injection style questions asking the assistant to reveal another farmer's data. | I48: Assistant refuses and does not disclose any other farmer's private information under any prompt phrasing. | J48: Functional | K48: Not Run
A49: TC-FR-045 | B49: Weather Intelligence | C49: FR-067, FR-068 | D49: Must | E49: P0 | F49: Twin stores current/forecast weather with required fields | G49: A farm with a valid location and a working weather provider. | H49: 1. Refresh the twin. 2. Inspect the weather section. | I49: Current and forecast weather are stored, including temperature, rain probability, rainfall, humidity, wind, extreme weather alerts, and forecast trends where the provider supplies them. | J49: Functional | K49: Fail | L49: M-1 | M49: Only a bare 'Clear' forecast string was ever observed; no temperature, rain probability, humidity, or wind fields seen on any screen.
A50: TC-FR-046 | B50: Weather Intelligence | C50: FR-069 | D50: Must | E50: P1 | F50: Weather changes dynamically influence recommendations/alerts | G50: A farm with an irrigation plan step scheduled, and a forecast showing significant rain incoming. | H50: 1. Trigger/await a twin refresh that picks up the new rain forecast. 2. Check plan guidance and alerts. | I50: System revises guidance (e.g., delay irrigation) and/or raises an alert reflecting the updated forecast. | J50: Functional | K50: Not Run
A51: TC-FR-047 | B51: Weather Intelligence | C51: FR-070 | D51: Must | E51: P0 | F51: Weather provider swappable without client changes | G51: Admin access to provider configuration. | H51: 1. Switch the configured weather provider to an alternate one. 2. Use the farmer app without any client update. | I51: Weather data continues to populate correctly with no farmer-client code change required. | J51: Functional | K51: Not Run
A52: TC-FR-048 | B52: Soil Intelligence | C52: FR-071 | D52: Must | E52: P1 | F52: Twin maintains available soil attributes | G52: A farm with a working soil/agri provider and/or farmer-entered soil-test data. | H52: 1. Refresh the twin and inspect the soil section. | I52: Soil type, texture, pH, organic matter, nutrients, and other available characteristics are shown where obtainable. | J52: Functional | K52: Blocked | L52: H-1 | M52: No soil entry UI exists — the /soil page renders only a heading and a Back link. See H-1 step 4.
A53: TC-FR-049 | B53: Soil Intelligence | C53: FR-072 | D53: Must | E53: P0 | F53: Data provenance is distinguished and labeled | G53: A farm with soil data from a third-party estimate and a separate farmer-entered soil-test result. | H53: 1. View both soil values in the UI. | I53: Each value is clearly labeled with its provenance: farmer-provided, third-party estimated, or observed/measured. | J53: Functional | K53: Blocked | L53: H-1 | M53: Cannot enter soil data of any provenance to test labeling — see H-1 step 4.
A54: TC-FR-050 | B54: Soil Intelligence | C54: FR-073 | D54: Must | E54: P1 | F54: Farmer-entered soil test takes precedence in recommendation weighting | G54: A farm with a third-party soil estimate already present. | H54: 1. Enter a soil-test result that differs from the third-party estimate. 2. Request a new plan/recommendation. | I54: Farmer-provided/measured soil data is used preferentially over the third-party estimate in generating the recommendation. | J54: Functional | K54: Blocked | L54: H-1 | M54: No soil-entry form exists to submit a farmer soil test. See H-1 step 4.
A55: TC-FR-051 | B55: Soil Intelligence | C55: FR-074 | D55: Should | E55: P0 | F55: Unknown soil never blocks plan generation | G55: A farm with soil marked as unknown/unset. | H55: 1. Request plan generation. | I55: Plan is still generated, using AI inference or soil-robust guidance, without being blocked by the missing soil data. | J55: Functional | K55: Pass | M55: Wizard generated a plan with soil left as 'unknown'.
A56: TC-FR-052 | B56: Water Intelligence | C56: FR-075, FR-076 | D56: Must | E56: P1 | F56: Multiple water sources with full attribute set | G56: Authenticated farmer editing a farm. | H56: 1. Add a tube well source with type, availability, seasonal availability, capacity, reliability, irrigation method, and fields served. 2. Add a second source of a different type (e.g., rainwater). | I56: Both sources are stored with all supplied attributes and correctly linked to the fields/areas they serve. | J56: Functional | K56: Fail | L56: H-1 | M56: Add-water-source form resets to blank on submit; nothing persists. See H-1 step 2.
A57: TC-FR-053 | B57: Water Intelligence | C57: FR-077 | D57: Must | E57: P1 | F57: Recommendations consider water constraints | G57: A farm where total water capacity is insufficient for all high-water-demand crop candidates. | H57: 1. Request a crop/portfolio recommendation. | I57: Recommendation favors lower water-demand crops or flags the constraint rather than recommending an infeasible high-water plan. | J57: Functional | K57: Blocked | L57: H-1 | M57: No water source can be persisted to test constraint-aware recommendations against.
A58: TC-FR-054 | B58: Water Intelligence | C58: FR-078 | D58: Should | E58: P1 | F58: Assistant/alerts answer field- and production-area-level irrigation questions correctly | G58: A farm with an open field and a shed, each with distinct water/weather/growth-stage context. | H58: 1. Ask the assistant an irrigation question about the open field. 2. Ask the same style of question about the shed. | I58: Each answer uses the correct production-area context (e.g., shed humidity vs open-field rain forecast) to advise on irrigation. | J58: Functional | K58: Blocked | L58: H-1 | M58: Only one production area exists per farm — can't compare shed vs open-field irrigation answers.
A59: TC-FR-055 | B59: Yield & Economic Intelligence | C59: FR-011 | D59: Should | E59: P0 | F59: Plan includes yield/harvest prediction with confidence | G59: A generated plan for a farm with sufficient twin context. | H59: 1. View the plan's yield section. | I59: Yield/harvest prediction is shown along with confidence level and stated assumptions. | J59: Functional | K59: Blocked | L59: H-1 | M59: Needs a real crop zone with expected yield — zone creation fails. See H-1.
A60: TC-FR-056 | B60: Yield & Economic Intelligence | C60: FR-079, FR-080 | D60: Must | E60: P1 | F60: Reference gross value computed and labeled as historical, not guaranteed | G60: A field with an expected yield and a matching government reference rate available. | H60: 1. View the field/crop's economic summary. | I60: Reference Gross Value = Expected Yield × Government Reference Rate is shown, explicitly labeled as a historical reference value, never presented as a guaranteed future price. | J60: Functional | K60: Blocked | L60: H-1 | M60: Needs a real crop zone with expected yield — zone creation fails. See H-1.
A61: TC-FR-057 | B61: Yield & Economic Intelligence | C61: FR-081 | D61: Must | E61: P1 | F61: Comparative crop economics table | G61: A portfolio recommendation covering multiple candidate crops. | H61: 1. View the economics comparison table. | I61: Table presents yield, reference rate, expected gross value, and risk side-by-side for the candidate crops. | J61: Functional | K61: Blocked | L61: H-1 | M61: Needs a portfolio of real candidate crops — zone creation fails. See H-1.
A62: TC-FR-058 | B62: Yield & Economic Intelligence | C62: FR-082 | D62: Should | E62: P1 | F62: Estimated production cost incorporated for net-value framing | G62: A field with an entered or modeled production cost. | H62: 1. View the economic summary with cost data present. | I62: Net-value framing (gross value minus estimated cost) is shown or clearly derivable, using the provided/modeled cost. | J62: Functional | K62: Blocked | L62: H-1 | M62: Needs a real field with cost data — zone creation fails. See H-1.
A63: TC-FR-059 | B63: Yield & Economic Intelligence | C63: FR-083 | D63: Must | E63: P1 | F63: Admin manages government reference rate datasets | G63: Admin console access. | H63: 1. As admin, add/update a government reference rate for a crop with an effective period. 2. Confirm the new rate is used in a fresh economic computation for that crop. | I63: Rate is stored by crop and effective period and is reflected in subsequent economic calculations. | J63: Functional | K63: Blocked | L63: H-3 | M63: Admin console sign-in never proceeds. See H-3.
A64: TC-FR-060 | B64: Nearby Farm Intelligence | C64: FR-033, FR-034 | D64: Should | E64: P1 | F64: Blended AI + regional suggestions, degrading gracefully when sparse | G64: One region with ample nearby-farm data, another region with very few farms. | H64: 1. Request crop suggestions in the data-rich region. 2. Request crop suggestions in the sparse region. | I64: Rich region: suggestions blend AI reasoning with anonymized regional data. Sparse region: suggestions degrade to AI-only and are clearly labeled as such. | J64: Functional | K64: Blocked | L64: Missing feature (FR-033/034) | M64: No 'similar/nearby farms' screen or entry point found anywhere in the app. See report 'Features not yet built'.
A65: TC-FR-061 | B65: Nearby Farm Intelligence | C65: FR-035 | D65: Must | E65: P0 | F65: Only aggregated, anonymized regional data exposed | G65: Multiple farms in the same region. | H65: 1. View 'farms similar to yours nearby' or regional insight output. 2. Inspect underlying API payload for identifying details. | I65: Only aggregate statistics are shown/returned; no individual farmer identity or private farm detail is ever exposed. | J65: Functional | K65: Blocked | L65: Missing feature (FR-035) | M65: No nearby-farm insight screen exists to inspect. See report 'Features not yet built'.
A66: TC-FR-062 | B66: Nearby Farm Intelligence | C66: FR-084, FR-085 | D66: Should | E66: P1 | F66: Similarity factors and aggregated-statement UI | G66: Farms of similar size/soil/climate in one region. | H66: 1. View the 'similar farms nearby' insight. | I66: Similarity considers proximity, size, soil, climate, water, crop selection, season; insight is presented purely as an aggregated statement (e.g., percentages/common patterns), never individual records. | J66: Functional | K66: Blocked | L66: Missing feature (FR-084/085) | M66: No 'similar farms nearby' insight UI found. See report 'Features not yet built'.
A67: TC-FR-063 | B67: Nearby Farm Intelligence | C67: FR-108 | D67: Should | E67: P1 | F67: Nearby-farm aggregates feed neighbouring-crop compatibility without exposing identities | G67: A region with nearby-farm crop aggregate data available. | H67: 1. View neighbouring-crop compatibility for a field that relies on nearby-farm signals. | I67: Compatibility insight is informed by the aggregate but never states which specific neighbour grows which crop. | J67: Functional | K67: Blocked | L67: Missing feature (FR-108) | M67: No neighbouring-crop compatibility screen found that uses this signal. See report 'Features not yet built'.
... A69: TC-FR-065 | B69: Experimental Farm | C69: FR-088 | D69: Must | E69: P1 | F69: Full experimental workflow end to end | G69: An experimental production area with an AI-identified candidate crop. | H69: 1. Progress through: AI identification → local condition comparison → yield/profit/risk estimate → small-area recommendation → farmer approval → season tracking → record actual outcome → compare to prediction. | I69: Every workflow stage completes and the final predicted-vs-actual comparison is recorded and feeds the Farm Learning Loop. | J69: Functional | K69: Blocked | L69: Missing feature (FR-086-089) | M69: No identify->compare->estimate->approve->track->compare-to-actual workflow exists in the UI. See report 'Features not yet built'.
A70: TC-FR-066 | B70: Experimental Farm | C70: FR-089 | D70: Should | E70: P1 | F70: Experimental candidates include uncommon/high-risk options | G70: An experimental area awaiting a crop candidate. | H70: 1. Request an experimental crop suggestion. | I70: Suggestion pool may include uncommon, newly introduced, AI-recommended, climate-analogous, or higher-risk/high-value candidates, not just mainstream crops. | J70: Functional | K70: Not Run
A71: TC-FR-067 | B71: Farm Learning Loop | C71: FR-090 | D71: Must | E71: P1 | F71: Record actual yield/cost/outcome per field/season | G71: A field with a completed season and a prior predicted yield. | H71: 1. Enter actual yield, cost, and outcome for the season. | I71: Actual values are recorded against the correct field and season. | J71: Functional | K71: Blocked | L71: Missing feature (FR-090-092) | M71: No 'record actual outcome' UI found anywhere. See report 'Features not yet built'.
A72: TC-FR-068 | B72: Farm Learning Loop | C72: FR-091 | D72: Must | E72: P1 | F72: Predicted vs actual comparison improves future recommendations | G72: A field with both predicted and newly recorded actual outcomes. | H72: 1. View the predicted-vs-actual comparison with an optional reason code. 2. Request a new recommendation for the same field/crop in a later season. | I72: Difference and reason code are stored; the subsequent recommendation reflects the learned adjustment for that farm. | J72: Functional | K72: Blocked | L72: Missing feature (FR-090-092) | M72: No 'record actual outcome' UI found anywhere. See report 'Features not yet built'.
A73: TC-FR-069 | B73: Farm Learning Loop | C73: FR-092 | D73: Should | E73: P2 | F73: Multi-season Farm Intelligence History summary | G73: A farm with three or more completed seasons of recorded outcomes. | H73: 1. View the Farm Intelligence History summary. | I73: Performance trends across seasons are summarized clearly (e.g., yield trend, cost trend). | J73: Functional | K73: Blocked | L73: Missing feature (FR-090-092) | M73: Depends on recorded outcomes, which have no UI to enter. See report 'Features not yet built'.
A74: TC-FR-070 | B74: Alerts & Recommendations | C74: FR-036 | D74: Should | E74: P0 | F74: Dashboard surfaces alerts (weather/calendar/pest) | G74: A farm with an upcoming plan-calendar reminder and adverse weather forecast. | H74: 1. Open the dashboard. | I74: Alerts area surfaces relevant weather, plan-calendar, and seasonal/pest alerts (on-load computation acceptable for P0). | J74: Functional | K74: Pass | M74: Alerts area present and surfaced relevant items on the dashboard.
A75: TC-FR-071 | B75: Alerts & Recommendations | C75: FR-037 | D75: Should | E75: P1 | F75: Alerts persist with read/unread state | G75: One or more alerts exist for a farm. | H75: 1. Mark an alert as read. 2. Reload the app/dashboard. | I75: Read/unread state persists correctly across sessions. | J75: Functional | K75: Pass | M75: Marked an alert read; state persisted across reload — one of only two mutations confirmed to actually persist (see H-1 note).
A76: TC-FR-072 | B76: Alerts & Recommendations | C76: FR-093 | D76: Must | E76: P1 | F76: Continuous evaluation produces actionable 'what to do next' recommendations | G76: A farm with a twin state change (e.g., new weather data). | H76: 1. Trigger scheduled evaluation (or wait for it) after the twin change. | I76: A new actionable recommendation is produced answering what the farmer should do next given the change. | J76: Functional | K76: Not Run
A77: TC-FR-073 | B77: Alerts & Recommendations | C77: FR-094 | D77: Must | E77: P1 | F77: Critical weather/risk alerts prioritized and localized | G77: A farm facing a severe weather event in the forecast, farmer's language set to Urdu. | H77: 1. Trigger the alert evaluation. | I77: Critical alert appears prioritized above routine alerts and is rendered in Urdu (RTL). | J77: Functional | K77: Not Run
A78: TC-FR-074 | B78: Alerts & Recommendations | C78: FR-095 | D78: Must | E78: P0 | F78: Alert/recommendation failure never blocks core viewing | G78: Alert/recommendation engine forced to fail (simulated). | H78: 1. Simulate a failure in alert computation. 2. Attempt to view the farm/twin. | I78: Farm and twin views load normally; only the alerts widget shows a graceful failure state. | J78: Functional | K78: Not Run
A79: TC-FR-075 | B79: History & Analytics | C79: FR-013, FR-014 | D79: Must | E79: P0 | F79: Farm profiles, production areas, fields, and plans are saved and revisitable | G79: A farmer has created a farm with production areas/fields and generated a plan. | H79: 1. Log out and log back in. 2. Navigate to the farm, its production areas/fields, and the saved plan. | I79: All previously saved data and the generated plan are retrievable exactly as left. | J79: Functional | K79: Pass | M79: Logged out and back in — farms and the generated plan were retrievable exactly as left.
A80: TC-FR-076 | B80: History & Analytics | C80: FR-026, FR-027 | D80: Must | E80: P0 | F80: Multiple farms per farmer; edits create new plan versions without destroying history | G80: A farmer with two farms, one having two prior plan versions. | H80: 1. Create a second farm. 2. Edit farm/production-area/field details on the first farm and regenerate the plan. | I80: Both farms are retained independently; regeneration creates a new plan version while all prior plan versions remain accessible. | J80: Functional | K80: Not Run
A81: TC-FR-077 | B81: History & Analytics | C81: FR-028, FR-120 | D81: Should | E81: P0/P1 | F81: Dashboard lists farms with twin/plan/assistant/alerts entry and environment breakdown | G81: A farmer with at least one farm containing multiple production area types. | H81: 1. Open the farms dashboard. | I81: Each farm is listed with access to twin summary, latest plan, assistant entry, and alerts; production-environment breakdown (open/protected/experimental totals, active crops, water status, weather risk, expected yield, reference value, Green Farm Score) is shown when available. | J81: Functional | K81: Pass | M81: Multi-farm dashboard with per-farm entry points confirmed present and working.
A82: TC-FR-078 | B82: History & Analytics | C82: FR-096 | D82: Must | E82: P1 | F82: Seasons, crops, yield, cost, outcomes tracked for analytics | G82: A farm with two completed seasons. | H82: 1. View farm performance analytics. | I82: Season-by-season crops, yield, costs, and outcomes are tracked and presented for the owning farmer only. | J82: Functional | K82: Not Run
A83: TC-FR-079 | B83: Localization | C83: FR-015 | D83: Must | E83: P0 | F83: Full core flow available in Urdu and English | G83: A new farmer account. | H83: 1. Complete onboarding, farm creation, plan generation, and dashboard viewing entirely in Urdu. 2. Repeat in English. | I83: Every screen in the core flow is fully localized and functional in both languages, with correct RTL layout for Urdu. | J83: Functional | K83: Fail | L83: H-2 | M83: Selecting Urdu in Settings has zero effect anywhere: document.documentElement.lang/dir stay 'en'/'ltr', localStorage hv_farmer_language stays 'en', and the saved profile's language field stays 'en' — confirmed via direct DOM/localStorage inspection before and after toggling.
A84: TC-FR-080 | B84: Localization | C84: FR-016 | D84: Must | E84: P0 | F84: Language choice persists across sessions | G84: A farmer sets language to Urdu. | H84: 1. Set language to Urdu. 2. Log out and log back in on the same or a different device. | I84: App reopens in Urdu without requiring the farmer to reselect it. | J84: Functional | K84: Fail | L84: H-2 | M84: Moot in practice — the toggle never sets any state to persist in the first place (see above).
A85: TC-FR-081 | B85: Administration | C85: FR-038 | D85: Should | E85: P1 | F85: Web-only admin console available | G85: Admin credentials. | H85: 1. Log into the admin console via a browser. 2. Attempt to access the same console URL from a mobile app context. | I85: Admin console is accessible and functional on web; it is not exposed as part of the farmer mobile app. | J85: Functional | K85: Fail | L85: H-3 | M85: Admin login never proceeds past /admin/login with the on-screen demo credentials, via button click or Enter key. See H-3.
A86: TC-FR-082 | B86: Administration | C86: FR-039 | D86: Should | E86: P1 | F86: Admin curates crop, seed variety, compatibility, and production-area-type catalogs | G86: Admin console access. | H86: 1. Add a new crop to the catalog. 2. Add a new seed variety linked to it. 3. Add a companion-planting rule. 4. Add a new production area type. | I86: All four catalog additions succeed and become selectable/usable in the farmer-facing app. | J86: Functional | K86: Blocked | L86: H-3 | M86: Admin console sign-in never proceeds. See H-3.
A87: TC-FR-083 | B87: Administration | C87: FR-040 | D87: Should | E87: P1 | F87: Admin reviews sampled/flagged AI outputs | G87: One or more AI-generated plans/assistant answers exist, at least one flagged. | H87: 1. As admin, open the AI output review queue. 2. Review a flagged plan/assistant answer. | I87: Sampled and flagged outputs are visible to admin for quality review. | J87: Functional | K87: Blocked | L87: H-3 | M87: Admin console sign-in never proceeds. See H-3.
A88: TC-FR-084 | B88: Administration | C88: FR-041 | D88: Should | E88: P1 | F88: Admin views usage and LLM cost analytics | G88: Some LLM usage has occurred in the system. | H88: 1. As admin, open usage/cost analytics. | I88: Usage volume and LLM cost figures are visible and broken down meaningfully (e.g., by endpoint/time period). | J88: Functional | K88: Blocked | L88: H-3 | M88: Admin console sign-in never proceeds. See H-3.
A89: TC-FR-085 | B89: Administration | C89: FR-042 | D89: Must | E89: P0 | F89: Admin auth stronger than farmer OTP; role checks and audit log on every admin endpoint | G89: Admin and non-admin accounts exist. | H89: 1. Attempt to log into the admin console using farmer OTP-style auth. 2. Log in with proper admin credentials (e.g., email/password + MFA). 3. Perform an admin action (e.g., edit a government rate). 4. Check the audit log. | I89: Farmer OTP cannot access the admin console; proper admin auth succeeds; every admin endpoint enforces role checks; the performed action appears in the audit log with actor, action, target, and timestamp. | J89: Functional | K89: Blocked | L89: H-3 | M89: Admin console sign-in never proceeds, so role checks/audit logging behind it are untestable. See H-3.
A90: TC-FR-086 | B90: Administration | C90: FR-097 | D90: Should | E90: P1 | F90: Admin configures provider feature flags | G90: Admin console access. | H90: 1. Toggle OTP_MODE between mock and live. 2. Toggle a weather/soil enrichment feature flag. | I90: Flags take effect for subsequent requests without requiring a farmer-client update. | J90: Functional | K90: Blocked | L90: H-3 | M90: Admin console sign-in never proceeds. See H-3.
A91: TC-FR-087 | B91: Platform Parity | C91: FR-043, FR-098 | D91: Must | E91: P0/P1 | F91: Equivalent functionality across web and mobile on shared backend | G91: A farmer account used on both a mobile client and a web client. | H91: 1. Perform the same core farm-management action on mobile. 2. Perform an equivalent action on web. 3. (P1) Compare assistant and twin views on both platforms. | I91: P0: mobile-first core APIs work identically on web for the same scope. P1: full parity is reached, including assistant and twin views, both backed by the same API contracts. | J91: Functional | K91: Not Run
A92: TC-FR-088 | B92: Protected Farming | C92: FR-121, FR-122 | D92: Must | E92: P1 | F92: Create/manage protected production areas with crop zones | G92: Authenticated farmer. | H92: 1. Create a shed production area. 2. Create a greenhouse production area. 3. Create a tunnel/polyhouse production area. 4. Add one or more crop zones to each. | I92: All three protected-area types can be created and each holds one or more crop zones correctly. | J92: Functional | K92: Blocked | L92: H-1 | M92: Shed/Greenhouse/Tunnel area types are selectable, but Add-area submission fails silently for all of them. See H-1 step 1.
A93: TC-FR-089 | B93: Protected Farming | C93: FR-123 | D93: Should | E93: P1 | F93: Applicable protected attributes stored where available, none mandatory | G93: A shed production area being configured. | H93: 1. Enter structure type, covered area, crop(s), growing method, growing medium, temperature, humidity, ventilation, irrigation, water source, planting date, growth stage, expected yield, production cost, resource consumption — leaving several fields blank. 2. Save. | I93: All supplied attributes are stored; the area saves successfully despite the missing (non-mandatory) attributes. | J93: Functional | K93: Blocked | L93: H-1 | M93: No protected area can be created to configure attributes on. See H-1.
A94: TC-FR-090 | B94: Protected Farming | C94: FR-124 | D94: Must | E94: P1 | F94: Protected-area attributes carry provenance and are never presented as measurements when estimated | G94: A shed with a third-party-estimated temperature value and no sensor. | H94: 1. View the shed's temperature attribute in the UI. | I94: Value is clearly labeled with its provenance (e.g., third_party_estimate) and is never presented as an on-site measurement. | J94: Functional | K94: Blocked | L94: H-1 | M94: No protected area can be created to inspect attribute provenance on. See H-1.
A95: TC-FR-091 | B95: Protected Farming | C95: FR-125, FR-118 | D95: Must | E95: P1 | F95: Environment-aware AI recommendations for protected crops | G95: A shed cucumber crop zone with temperature/humidity data, versus an open-field cucumber zone. | H95: 1. Request care guidance/plan content for the shed cucumber. 2. Request the same for the open-field cucumber. | I95: Guidance differs appropriately and is grounded in each zone's actual environment (temperature/humidity/ventilation/growing medium for the shed vs outdoor weather for the open field). | J95: Functional | K95: Blocked | L95: H-1 | M95: Needs a real shed crop zone with temperature/humidity data to compare against an open-field crop zone — zone creation fails. See H-1.
A96: TC-FR-092 | B96: Protected Farming | C96: FR-126 | D96: Must | E96: P0 | F96: Data model represents protected/experimental areas even before rich P1 UX | G96: A P0-stage build without full protected-farming UI richness. | H96: 1. Create a shed, greenhouse, tunnel, and experimental production area using whatever P0 UI/API surface exists. | I96: Each type can be represented in the data model in P0, even if the rich attribute-entry UX ships later in P1. | J96: Functional | K96: Blocked | L96: H-1 | M96: Area creation fails at the UI/API layer tested. See H-1.
A97: TC-FR-093 | B97: Green Farm Intelligence | C97: FR-127 | D97: Must | E97: P1 | F97: Green Farm Intelligence uses only available data, never fabricated | G97: A farm missing several sustainability-relevant data points (e.g., no rotation history). | H97: 1. View the Green Farm Intelligence output. | I97: Score/analysis is computed only from available twin data; missing dimensions are omitted or marked unavailable rather than invented. | J97: Functional | K97: Pass | M97: Dedicated /green page correctly marks unscored dimensions 'Unavailable' rather than guessing.
A98: TC-FR-094 | B98: Green Farm Intelligence | C98: FR-128 | D98: Should | E98: P1 | F98: Sustainability dimensions surfaced where data exists | G98: A farm with water-efficiency and crop-diversity data available, but no soil-health-practice data. | H98: 1. View the sustainability dimension breakdown. | I98: Water efficiency and crop diversity dimensions are shown with values; soil-health-practice dimension is marked unavailable rather than guessed. | J98: Functional | K98: Pass | M98: Only the 2 dimensions with real data (production area size, crop-plan estimate) were scored; others marked unavailable.
A99: TC-FR-095 | B99: Green Farm Intelligence | C99: FR-129 | D99: Must | E99: P1 | F99: Explainable Green Farm Score with contributing factors and recalculation | G99: A farm with a computed Green Farm Score. | H99: 1. View the score breakdown (contributing factors, improvement areas, measured vs estimated). 2. Change a relevant twin input (e.g., add a water-efficient irrigation method). 3. Recheck the score. | I99: Factors and improvement areas are shown; measured vs estimated inputs are distinguished; the score recalculates after the relevant twin data changes. | J99: Functional | K99: Fail | L99: M-2 | M99: Score changed from 33 to 49 across two reloads of the same farm with zero data changes in between — recalculation is not stable/deterministic. See M-2.
A100: TC-FR-096 | B100: Green Farm Intelligence | C100: FR-130 | D100: Must | E100: P1 | F100: Assistant answers sustainability questions with proactive recommendations | G100: A farm with a computed Green Farm Score and sufficient supporting data. | H100: 1. Ask the assistant 'Why is my Green Farm Score low?' and 'How can I reduce water usage?' | I100: Assistant explains contributing factors and offers actionable, data-grounded recommendations; may proactively suggest improvements when data supports it. | J100: Functional | K100: Pass | M100: Asked 'Is my Green Farm Score accurate given I have no soil or water data?' live — assistant gave a grounded, data-referenced answer with an improvement checklist.
A101: TC-FR-097 | B101: Green Farm Intelligence | C101: FR-131 | D101: Must | E101: P1 | F101: Green recommendations labeled by source type with disclaimers | G101: A Green Farm recommendation generated from a mix of rule-based and AI-generated logic. | H101: 1. View a green recommendation. | I101: Recommendation indicates whether it is data-driven, rule-based, AI-generated, and/or based on estimated third-party information, and includes an advisory disclaimer. | J101: Functional | K101: Not Run
A102: TC-FR-098 | B102: Green Farm Intelligence | C102: FR-132 | D102: Must | E102: P1 | F102: No certification claims anywhere in Green Score UI/content | G102: The Green Farm Score feature across all farmer-facing surfaces. | H102: 1. Review all Green Farm Score screens, tooltips, exports, and assistant answers referencing the score. | I102: No wording anywhere states or implies government, environmental, or scientific certification, or guaranteed sustainability compliance. | J102: Functional | K102: Pass | M102: No certification/guarantee language observed on any Green Score screen or assistant answer reviewed.
...

Sheet Non-Functional Test Cases
A1: HAPPY VEGGIE — Non-Functional Test Cases
A2: Derived from HAPPY-VEGGIE-SRS.md v1.3 (github.com/Arsal0336/happy-veggies)
A4: Test Case ID | B4: Module | C4: Req ID(s) | D4: Priority | E4: Phase | F4: Test Case Title | G4: Preconditions | H4: Test Steps | I4: Expected Result | J4: Test Type | K4: Status | L4: Defect Ref | M4: Actual Result / Retest Notes (5 Sept 2026 run)
A5: TC-NFR-001 | B5: NFR | C5: NFR-001 | D5: Must | E5: P0 | F5: Plan generation completes within ~60s (p95) | G5: Normal operating conditions, LLM provider healthy. | H5: 1. Trigger plan generation 20+ times under normal load. 2. Measure p95 latency. | I5: p95 completion time is within the documented SLO (~60s target); actual SLO is recorded in the ops runbook. | J5: Performance | K5: Not Run
A6: TC-NFR-002 | B6: NFR | C6: NFR-002 | D6: Must | E6: P0 | F6: Mobile-first responsive UI on low/mid-range Android | G6: A low-to-mid-range Android test device or emulator profile. | H6: 1. Load core farmer flows on the low/mid-range device profile. | I6: UI renders usably with responsive layout and acceptable performance. | J6: Usability | K6: Not Run
A7: TC-NFR-003 | B7: NFR | C7: NFR-003 | D7: Must | E7: P0 | F7: New farmer reaches a plan without external assistance | G7: A first-time user with no prior product training. | H7: 1. Have an unassisted new user attempt onboarding through to receiving a plan. | I7: User completes onboarding and receives a plan without needing outside help/documentation. | J7: Usability | K7: Not Run
A8: TC-NFR-004 | B8: NFR | C8: NFR-004 | D8: Must | E8: P0 | F8: All farmer UI and generated content (incl. PDFs) render correctly Urdu RTL / English LTR | G8: Generated plan with PDF export enabled. | H8: 1. View core screens and export a plan to PDF in Urdu. 2. Repeat in English. | I8: Urdu renders correct RTL layout throughout, including the PDF; English renders correct LTR; no mirrored/garbled text. | J8: Localization | K8: Fail | L8: H-2 | M8: Confirmed at the state level: htmlLang/dir, hv_farmer_language, and profile.language all stay 'en'/'ltr' after selecting Urdu. PDF export doesn't exist yet either (see M-6), so it's untestable in Urdu.
A9: TC-NFR-005 | B9: NFR | C9: NFR-005 | D9: Must | E9: P0 | F9: Clear retry path on LLM/feed failure/timeout | G9: LLM or weather/soil feed forced to time out. | H9: 1. Trigger the timeout during plan generation or twin refresh. | I9: A clear, localized retry option is presented; core flow proceeds without the unavailable enrichment rather than hard-failing. | J9: Reliability | K9: Not Run
A10: TC-NFR-006 | B10: NFR | C10: NFR-006 | D10: Must | E10: P0 | F10: Phone/location/farm data secured; access owner/admin-restricted; aggregates never expose individuals | G10: Farmer data plus a regional aggregate feature. | H10: 1. Attempt unauthorized access to another farmer's phone/location/farm data. 2. Inspect a regional aggregate response for identifying detail. | I10: Unauthorized access is denied; aggregate responses contain no individual-identifying information. | J10: Security | K10: Not Run
A11: TC-NFR-007 | B11: NFR | C11: NFR-007 | D11: Must | E11: P0 | F11: LLM usage token-bounded per request type; cost visible to admin | G11: Admin console with LLM usage. | H11: 1. Trigger an LLM-backed request and confirm a token bound is enforced. 2. View admin cost dashboard. | I11: Requests respect configured token bounds per request type; cost figures are visible to admins. | J11: Performance | K11: Not Run
A12: TC-NFR-008 | B12: NFR | C12: NFR-008 | D12: Must | E12: P0 | F12: Privileged admin actions audit-logged | G12: Admin performs a privileged action (e.g., rate update, catalog edit). | H12: 1. Perform the action. 2. Inspect the audit log. | I12: Action appears in the audit log with actor, action, target, and timestamp. | J12: Security | K12: Not Run
A13: TC-NFR-009 | B13: NFR | C13: NFR-009 | D13: Must | E13: P0 | F13: Farmer clients share API contracts and localization resources | G13: Web and mobile clients pointed at the same backend/localization resource bundle. | H13: 1. Compare API contract versions and localization strings used by both clients. | I13: Both clients consume identical API contracts and localization resources with no platform-specific drift. | J13: Compatibility | K13: Not Run
A14: TC-NFR-010 | B14: NFR | C14: NFR-010 | D14: Must | E14: P1 | F14: API availability ≥ 99.5% monthly excluding planned maintenance | G14: Production monitoring data for a full calendar month. | H14: 1. Review uptime monitoring/incident logs for the month. | I14: Measured availability meets or exceeds 99.5% excluding documented planned maintenance windows. | J14: Reliability | K14: Not Run
A15: TC-NFR-011 | B15: NFR | C15: NFR-011 | D15: Must | E15: P1 | F15: Assistant latency SLO (e.g., p95 ≤ 15s for non-tool-heavy turns) | G15: Normal load, assistant endpoint healthy. | H15: 1. Send 20+ non-tool-heavy assistant turns. 2. Measure first-token/short-answer p95 latency. | I15: p95 latency meets the defined SLO; longer analyses are handled as async jobs with progress indication. | J15: Performance | K15: Not Run
A16: TC-NFR-012 | B16: NFR | C16: NFR-012 | D16: Must | E16: P0 | F16: TLS in transit; secrets in a secret manager; least-privilege IAM; OWASP-aligned hardening | G16: Running API + infrastructure configuration. | H16: 1. Attempt a plaintext HTTP connection to the API. 2. Scan for secrets in client bundles/config. 3. Run an OWASP API security scan (authn/z, rate limiting, input validation) against key endpoints. | I16: Plaintext connections are rejected/redirected to TLS; no secrets found in clients; scan finds no high-severity OWASP API issues. | J16: Security | K16: Not Run
A17: TC-NFR-013 | B17: NFR | C17: NFR-013 | D17: Must | E17: P1 | F17: Structured logs/metrics/tracing for twin refresh, provider calls, LLM calls, errors; no secrets logged | G17: Twin refresh and an LLM call triggered. | H17: 1. Trigger a twin refresh and an assistant call. 2. Inspect logs, metrics, and traces. | I17: Structured log entries, metrics, and traces exist for each operation; no secret values appear in any log line. | J17: Observability | K17: Not Run
A18: TC-NFR-014 | B18: NFR | C18: NFR-014 | D18: Must | E18: P0 | F18: Privacy policy/consent for location & phone; documented deletion path | G18: A farmer requesting account/data deletion. | H18: 1. Review consent presented at signup for location/phone use. 2. Submit a data-deletion request. | I18: Consent is clearly presented before location/phone capture; deletion request is honored per the documented SLA (soft-delete/anonymize). | J18: Privacy/Compliance | K18: Not Run
A19: TC-NFR-015 | B19: NFR | C19: NFR-015 | D19: Must | E19: P1 | F19: Provider adapters isolated behind interfaces with circuit breakers/timeouts | G19: Weather provider forced to become slow/unresponsive. | H19: 1. Simulate a slow/unresponsive weather provider. 2. Observe system behavior over repeated calls. | I19: Calls time out and a circuit breaker trips after repeated failures, preventing cascading slowness elsewhere in the system. | J19: Reliability | K19: Not Run
A20: TC-NFR-016 | B20: NFR | C20: NFR-016 | D20: Should | E20: P1 | F20: Twin refresh and LLM jobs are asynchronously queueable under load | G20: A burst of twin-refresh/LLM requests exceeding immediate processing capacity. | H20: 1. Generate a burst of requests beyond normal capacity. | I20: Excess jobs queue and process asynchronously rather than failing outright or blocking the caller. | J20: Scalability | K20: Not Run
A21: TC-NFR-017 | B21: NFR | C21: NFR-017 | D21: Must | E21: P0 | F21: Advisory disclaimer on all AI yield/price/action advice | G21: Any generated plan, economics table, or assistant recommendation. | H21: 1. Inspect a plan, an economics table, and an assistant recommendation. | I21: Each surface includes a visible advisory disclaimer that the content is not a guarantee. | J21: Compliance | K21: Pass | M21: Disclaimer present on plan output, assistant answers, and Green Score explanations in every live check.
A22: TC-NFR-018 | B22: NFR | C22: NFR-018 | D22: Must | E22: P1 | F22: Automated backups with tested restore; documented RPO/RTO | G22: Production/staging database with backup automation configured. | H22: 1. Confirm automated backup job ran. 2. Perform a test restore into a non-production environment. 3. Measure time to restore and data currency. | I22: Restore succeeds; measured RPO/RTO are within the documented targets. | J22: Reliability | K22: Not Run
A23: TC-NFR-019 | B23: NFR | C23: NFR-019 | D23: Must | E23: P0 | F23: Rate limiting on OTP, LLM, and assistant endpoints per farmer/phone | G23: A single phone number/account. | H23: 1. Rapidly repeat OTP requests for the same phone number beyond the configured limit. 2. Repeat for assistant/LLM endpoints. | I23: Requests beyond the limit are throttled/rejected with a clear rate-limit response. | J23: Security | K23: Not Run
A24: TC-NFR-020 | B24: NFR | C24: NFR-020 | D24: Should | E24: P2 | F24: Core web flows meet WCAG 2.1 AA where feasible | G24: Core farmer web flows. | H24: 1. Run an automated accessibility audit (e.g., axe) plus manual keyboard/screen-reader spot checks on core flows. | I24: No critical WCAG 2.1 AA violations on core flows; issues found are documented for remediation. | J24: Accessibility | K24: Not Run
A25: TC-NFR-021 | B25: NFR | C25: NFR-021 | D25: Must | E25: P0 | F25: Stack compliance: ASP.NET Core + EF Core + CQRS + SQL Server; React functional components only | G25: Full backend and frontend source repositories. | H25: 1. Review backend for ASP.NET Core, EF Core migrations, and CQRS command/query handler structure. 2. Scan React source for any class components. | I25: Backend matches the mandated stack and CQRS pattern; no class components exist in either farmer or admin React apps. | J25: Architecture/Compliance | K25: Not Run
A26: TC-NFR-022 | B26: NFR | C26: NFR-022 | D26: Must | E26: P1 | F26: No fabricated sustainability/environment data; missing inputs marked unavailable | G26: A farm with partial protected-environment and sustainability data. | H26: 1. Inspect Green Farm Score and protected-area attribute displays for any value not traceable to a real input. | I26: Every displayed value traces to farmer-provided, third-party, observed, or system-derived data; anything missing is marked unavailable, never invented. | J26: Data Quality | K26: Not Run

Sheet External Interface Test Cases
A1: HAPPY VEGGIE — External Interface Test Cases
A2: Derived from HAPPY-VEGGIE-SRS.md v1.3 (github.com/Arsal0336/happy-veggies)
A4: Test Case ID | B4: Module | C4: Req ID(s) | D4: Priority | E4: Phase | F4: Test Case Title | G4: Preconditions | H4: Test Steps | I4: Expected Result | J4: Test Type | K4: Status | L4: Defect Ref | M4: Actual Result / Retest Notes (5 Sept 2026 run)
A5: TC-EIR-001 | B5: External Interfaces | C5: EIR-001 | D5: Must | E5: P0 | F5: Farmer UI available on web and mobile, responsive | G5: Web browser and mobile device/emulator. | H5: 1. Load the farmer app on web. 2. Load it on a mobile device. | I5: Both render correctly and responsively to their respective device sizes. | J5: Functional | K5: Not Run
A6: TC-EIR-002 | B6: External Interfaces | C6: EIR-002 | D6: Must | E6: P0 | F6: All farmer UI renders correctly Urdu RTL / English LTR incl. exports | G6: Core screens plus an exported document (PDF/plan). | H6: 1. View core screens and export a document in each language. | I6: Both languages render correctly, including exported documents. | J6: Functional | K6: Fail | L6: H-2 | M6: Same state-level evidence as NFR-004 — see H-2.
A7: TC-EIR-003 | B7: External Interfaces | C7: EIR-003 | D7: Must | E7: P0 | F7: Shared ASP.NET Core API consumed by farmer clients and privileged admin console | G7: Farmer client and admin console pointed at the same API base. | H7: 1. Call a farmer endpoint from the farmer client. 2. Call an admin-scoped endpoint from the admin console. | I7: Both consume the same shared ASP.NET Core backend; admin-scoped calls require privileged access. | J7: Functional | K7: Not Run
A8: TC-EIR-004 | B8: External Interfaces | C8: EIR-004 | D8: Must | E8: P0 | F8: LLM provider integration for plans, care guidance, assistant | G8: Configured LLM provider. | H8: 1. Trigger plan generation, care guidance, and an assistant query. | I8: All three features successfully call the configured LLM provider and return generated content. | J8: Functional | K8: Not Run
A9: TC-EIR-005 | B9: External Interfaces | C9: EIR-005 | D9: Must | E9: P0 | F9: Weather provider integration; failure doesn't block core CRUD/last-known twin | G9: Weather provider forced to fail. | H9: 1. Simulate weather provider failure. 2. Perform farm CRUD and view the twin. | I9: Farm CRUD succeeds normally; twin shows the last-known weather snapshot rather than blocking the view. | J9: Functional | K9: Not Run
A10: TC-EIR-006 | B10: External Interfaces | C10: EIR-006 | D10: Should | E10: P1 | F10: Soil/agri provider integration by coordinates, graceful degradation | G10: Soil provider forced to fail for a given farm's coordinates. | H10: 1. Simulate soil provider failure. 2. View the twin's soil section. | I10: Soil section degrades gracefully (e.g., marked unavailable) without blocking the rest of the twin. | J10: Functional | K10: Not Run
A11: TC-EIR-007 | B11: External Interfaces | C11: EIR-007 | D11: Must | E11: P0 | F11: Native GPS (mobile) / browser geolocation (web) integration | G11: Mobile device and web browser, each with location permission available. | H11: 1. Trigger location capture on mobile. 2. Trigger location capture on web. | I11: Both platforms successfully obtain and store device location via their respective native/browser APIs. | J11: Functional | K11: Not Run
A12: TC-EIR-008 | B12: External Interfaces | C12: EIR-008 | D12: Must | E12: P0 | F12: SMS/OTP live and mock modes behind config with identical client contracts | G12: Environment configurable between OTP_MODE=mock and live. | H12: 1. Run the OTP flow in mock mode. 2. Run the OTP flow in live mode (if available in a test environment). | I12: Both modes expose identical request/response contracts to the client; only the underlying delivery mechanism differs. | J12: Functional | K12: Not Run
A13: TC-EIR-009 | B13: External Interfaces | C13: EIR-009 | D13: Must | E13: P1 | F13: Government crop reference rate ingestion, labeled as reference values | G13: Admin rate ingestion tool/API. | H13: 1. Ingest a new government reference rate via admin upload/API. 2. View it surfaced in an economics computation. | I13: Rate is ingested successfully and always labeled as a historical reference value wherever displayed. | J13: Functional | K13: Not Run
A14: TC-EIR-010 | B14: External Interfaces | C14: EIR-010 | D14: Must | E14: P0 | F14: All external provider credentials stored server-side only | G14: Farmer client application bundle (web/mobile) and network traffic. | H14: 1. Inspect client bundle source/config and network requests from the client for any provider API key/secret. | I14: No weather/soil/LLM/SMS provider credential is ever present in a farmer client bundle or client-originated network call. | J14: Functional | K14: Not Run
